Metadata-Version: 2.1
Name: shuffle-dist-cards
Version: 0.1.1
Summary: Shuffle and distribute cards 
Home-page: UNKNOWN
Author: Ajinkya Joshi
Author-email: ajinkya.dj92@gmail.com
License: UNKNOWN
Platform: UNKNOWN
